[
  {
    "model_name": "CNN+GCN 4nb L3",
    "abl_id": "ABL-05",
    "model_group": "ResNet50",
    "description": "ResNet50-IBN + 4-neighbor + 3 layer GCN",
    "occlusion_level": 0,
    "mAP": 74.3696,
    "rank1": 94.27890014648438,
    "rank5": 97.61620330810547,
    "rank10": 98.331298828125
  },
  {
    "model_name": "CNN+GCN 4nb L3",
    "abl_id": "ABL-05",
    "model_group": "ResNet50",
    "description": "ResNet50-IBN + 4-neighbor + 3 layer GCN",
    "occlusion_level": 3,
    "mAP": 73.751,
    "rank1": 93.86170196533203,
    "rank5": 97.1989974975586,
    "rank10": 98.21219635009766
  },
  {
    "model_name": "CNN+GCN 4nb L3",
    "abl_id": "ABL-05",
    "model_group": "ResNet50",
    "description": "ResNet50-IBN + 4-neighbor + 3 layer GCN",
    "occlusion_level": 6,
    "mAP": 73.401,
    "rank1": 93.2061996459961,
    "rank5": 97.25859832763672,
    "rank10": 98.27179718017578
  },
  {
    "model_name": "CNN+GCN 4nb L3",
    "abl_id": "ABL-05",
    "model_group": "ResNet50",
    "description": "ResNet50-IBN + 4-neighbor + 3 layer GCN",
    "occlusion_level": 9,
    "mAP": 72.5692,
    "rank1": 93.02739715576172,
    "rank5": 96.96070098876953,
    "rank10": 97.97380065917969
  },
  {
    "model_name": "CNN+GCN 4nb L3",
    "abl_id": "ABL-05",
    "model_group": "ResNet50",
    "description": "ResNet50-IBN + 4-neighbor + 3 layer GCN",
    "occlusion_level": 12,
    "mAP": 71.8553,
    "rank1": 92.37190246582031,
    "rank5": 96.6626968383789,
    "rank10": 97.85459899902344
  },
  {
    "model_name": "CNN+GCN 4nb L3",
    "abl_id": "ABL-05",
    "model_group": "ResNet50",
    "description": "ResNet50-IBN + 4-neighbor + 3 layer GCN",
    "occlusion_level": 15,
    "mAP": 71.1505,
    "rank1": 91.5374984741211,
    "rank5": 95.768798828125,
    "rank10": 97.85459899902344
  },
  {
    "model_name": "CNN+GCN 4nb L3",
    "abl_id": "ABL-05",
    "model_group": "ResNet50",
    "description": "ResNet50-IBN + 4-neighbor + 3 layer GCN",
    "occlusion_level": 18,
    "mAP": 69.9481,
    "rank1": 91.0011978149414,
    "rank5": 96.36470031738281,
    "rank10": 97.85459899902344
  },
  {
    "model_name": "CNN+GCN 4nb L3",
    "abl_id": "ABL-05",
    "model_group": "ResNet50",
    "description": "ResNet50-IBN + 4-neighbor + 3 layer GCN",
    "occlusion_level": 21,
    "mAP": 68.8392,
    "rank1": 89.51129913330078,
    "rank5": 95.4708023071289,
    "rank10": 97.07990264892578
  },
  {
    "model_name": "CNN+GCN 4nb L3",
    "abl_id": "ABL-05",
    "model_group": "ResNet50",
    "description": "ResNet50-IBN + 4-neighbor + 3 layer GCN",
    "occlusion_level": 24,
    "mAP": 68.6128,
    "rank1": 89.98809814453125,
    "rank5": 95.35160064697266,
    "rank10": 97.49700164794922
  },
  {
    "model_name": "CNN+GCN 4nb L3",
    "abl_id": "ABL-05",
    "model_group": "ResNet50",
    "description": "ResNet50-IBN + 4-neighbor + 3 layer GCN",
    "occlusion_level": 27,
    "mAP": 66.5122,
    "rank1": 85.93560028076172,
    "rank5": 94.15969848632812,
    "rank10": 96.42430114746094
  },
  {
    "model_name": "CNN+GCN 4nb L3",
    "abl_id": "ABL-05",
    "model_group": "ResNet50",
    "description": "ResNet50-IBN + 4-neighbor + 3 layer GCN",
    "occlusion_level": 30,
    "mAP": 65.0935,
    "rank1": 85.69730377197266,
    "rank5": 93.26580047607422,
    "rank10": 95.94760131835938
  },
  {
    "model_name": "ViT+GCN 4nb L1",
    "abl_id": "ABL-02",
    "model_group": "ViT-Base",
    "description": "ViT-Base-768 + 4-neighbor + 1 layer GCN",
    "occlusion_level": 0,
    "mAP": 72.8176,
    "rank1": 94.69609832763672,
    "rank5": 97.91419982910156,
    "rank10": 98.98690032958984
  },
  {
    "model_name": "ViT+GCN 4nb L1",
    "abl_id": "ABL-02",
    "model_group": "ViT-Base",
    "description": "ViT-Base-768 + 4-neighbor + 1 layer GCN",
    "occlusion_level": 3,
    "mAP": 72.3157,
    "rank1": 93.86170196533203,
    "rank5": 97.97380065917969,
    "rank10": 98.98690032958984
  },
  {
    "model_name": "ViT+GCN 4nb L1",
    "abl_id": "ABL-02",
    "model_group": "ViT-Base",
    "description": "ViT-Base-768 + 4-neighbor + 1 layer GCN",
    "occlusion_level": 6,
    "mAP": 71.9098,
    "rank1": 93.74250030517578,
    "rank5": 97.61620330810547,
    "rank10": 98.74849700927734
  },
  {
    "model_name": "ViT+GCN 4nb L1",
    "abl_id": "ABL-02",
    "model_group": "ViT-Base",
    "description": "ViT-Base-768 + 4-neighbor + 1 layer GCN",
    "occlusion_level": 9,
    "mAP": 71.3752,
    "rank1": 92.9677963256836,
    "rank5": 97.49700164794922,
    "rank10": 98.5697021484375
  },
  {
    "model_name": "ViT+GCN 4nb L1",
    "abl_id": "ABL-02",
    "model_group": "ViT-Base",
    "description": "ViT-Base-768 + 4-neighbor + 1 layer GCN",
    "occlusion_level": 12,
    "mAP": 70.894,
    "rank1": 93.2061996459961,
    "rank5": 97.55660247802734,
    "rank10": 98.8676986694336
  },
  {
    "model_name": "ViT+GCN 4nb L1",
    "abl_id": "ABL-02",
    "model_group": "ViT-Base",
    "description": "ViT-Base-768 + 4-neighbor + 1 layer GCN",
    "occlusion_level": 15,
    "mAP": 69.793,
    "rank1": 92.19309997558594,
    "rank5": 97.02030181884766,
    "rank10": 98.39089965820312
  },
  {
    "model_name": "ViT+GCN 4nb L1",
    "abl_id": "ABL-02",
    "model_group": "ViT-Base",
    "description": "ViT-Base-768 + 4-neighbor + 1 layer GCN",
    "occlusion_level": 18,
    "mAP": 68.7895,
    "rank1": 90.94159698486328,
    "rank5": 96.42430114746094,
    "rank10": 98.15260314941406
  },
  {
    "model_name": "ViT+GCN 4nb L1",
    "abl_id": "ABL-02",
    "model_group": "ViT-Base",
    "description": "ViT-Base-768 + 4-neighbor + 1 layer GCN",
    "occlusion_level": 21,
    "mAP": 68.2155,
    "rank1": 91.06079864501953,
    "rank5": 96.36470031738281,
    "rank10": 97.79499816894531
  },
  {
    "model_name": "ViT+GCN 4nb L1",
    "abl_id": "ABL-02",
    "model_group": "ViT-Base",
    "description": "ViT-Base-768 + 4-neighbor + 1 layer GCN",
    "occlusion_level": 24,
    "mAP": 67.2313,
    "rank1": 89.92849731445312,
    "rank5": 95.88800048828125,
    "rank10": 97.73539733886719
  },
  {
    "model_name": "ViT+GCN 4nb L1",
    "abl_id": "ABL-02",
    "model_group": "ViT-Base",
    "description": "ViT-Base-768 + 4-neighbor + 1 layer GCN",
    "occlusion_level": 27,
    "mAP": 65.5309,
    "rank1": 88.73660278320312,
    "rank5": 95.11319732666016,
    "rank10": 97.73539733886719
  },
  {
    "model_name": "ViT+GCN 4nb L1",
    "abl_id": "ABL-02",
    "model_group": "ViT-Base",
    "description": "ViT-Base-768 + 4-neighbor + 1 layer GCN",
    "occlusion_level": 30,
    "mAP": 65.1272,
    "rank1": 88.55780029296875,
    "rank5": 94.51730346679688,
    "rank10": 96.72229766845703
  },
  {
    "model_name": "ViT+GCN 4nb L2",
    "abl_id": "ABL-11",
    "model_group": "ViT-Base",
    "description": "ViT-Base-768 + 4-neighbor + 2 layer GCN",
    "occlusion_level": 0,
    "mAP": 72.3393,
    "rank1": 93.92130279541016,
    "rank5": 97.55660247802734,
    "rank10": 98.80809783935547
  },
  {
    "model_name": "ViT+GCN 4nb L2",
    "abl_id": "ABL-11",
    "model_group": "ViT-Base",
    "description": "ViT-Base-768 + 4-neighbor + 2 layer GCN",
    "occlusion_level": 3,
    "mAP": 71.7216,
    "rank1": 93.38500213623047,
    "rank5": 97.31819915771484,
    "rank10": 98.5697021484375
  },
  {
    "model_name": "ViT+GCN 4nb L2",
    "abl_id": "ABL-11",
    "model_group": "ViT-Base",
    "description": "ViT-Base-768 + 4-neighbor + 2 layer GCN",
    "occlusion_level": 6,
    "mAP": 71.4294,
    "rank1": 93.32540130615234,
    "rank5": 97.4374008178711,
    "rank10": 98.62930297851562
  },
  {
    "model_name": "ViT+GCN 4nb L2",
    "abl_id": "ABL-11",
    "model_group": "ViT-Base",
    "description": "ViT-Base-768 + 4-neighbor + 2 layer GCN",
    "occlusion_level": 9,
    "mAP": 70.8486,
    "rank1": 91.89510345458984,
    "rank5": 97.02030181884766,
    "rank10": 98.331298828125
  },
  {
    "model_name": "ViT+GCN 4nb L2",
    "abl_id": "ABL-11",
    "model_group": "ViT-Base",
    "description": "ViT-Base-768 + 4-neighbor + 2 layer GCN",
    "occlusion_level": 12,
    "mAP": 70.4025,
    "rank1": 92.37190246582031,
    "rank5": 96.78189849853516,
    "rank10": 98.39089965820312
  },
  {
    "model_name": "ViT+GCN 4nb L2",
    "abl_id": "ABL-11",
    "model_group": "ViT-Base",
    "description": "ViT-Base-768 + 4-neighbor + 2 layer GCN",
    "occlusion_level": 15,
    "mAP": 69.6115,
    "rank1": 92.37190246582031,
    "rank5": 96.9011001586914,
    "rank10": 98.27179718017578
  },
  {
    "model_name": "ViT+GCN 4nb L2",
    "abl_id": "ABL-11",
    "model_group": "ViT-Base",
    "description": "ViT-Base-768 + 4-neighbor + 2 layer GCN",
    "occlusion_level": 18,
    "mAP": 68.677,
    "rank1": 91.06079864501953,
    "rank5": 96.18589782714844,
    "rank10": 97.91419982910156
  },
  {
    "model_name": "ViT+GCN 4nb L2",
    "abl_id": "ABL-11",
    "model_group": "ViT-Base",
    "description": "ViT-Base-768 + 4-neighbor + 2 layer GCN",
    "occlusion_level": 21,
    "mAP": 67.8862,
    "rank1": 90.94159698486328,
    "rank5": 95.94760131835938,
    "rank10": 97.55660247802734
  },
  {
    "model_name": "ViT+GCN 4nb L2",
    "abl_id": "ABL-11",
    "model_group": "ViT-Base",
    "description": "ViT-Base-768 + 4-neighbor + 2 layer GCN",
    "occlusion_level": 24,
    "mAP": 67.1726,
    "rank1": 89.27300262451172,
    "rank5": 95.58999633789062,
    "rank10": 97.91419982910156
  },
  {
    "model_name": "ViT+GCN 4nb L2",
    "abl_id": "ABL-11",
    "model_group": "ViT-Base",
    "description": "ViT-Base-768 + 4-neighbor + 2 layer GCN",
    "occlusion_level": 27,
    "mAP": 65.4607,
    "rank1": 89.27300262451172,
    "rank5": 95.70919799804688,
    "rank10": 96.84149932861328
  },
  {
    "model_name": "ViT+GCN 4nb L2",
    "abl_id": "ABL-11",
    "model_group": "ViT-Base",
    "description": "ViT-Base-768 + 4-neighbor + 2 layer GCN",
    "occlusion_level": 30,
    "mAP": 64.7639,
    "rank1": 87.18710327148438,
    "rank5": 94.27890014648438,
    "rank10": 96.96070098876953
  },
  {
    "model_name": "ViT+GCN kNN L1",
    "abl_id": "ABL-15",
    "model_group": "ViT-Base",
    "description": "ViT-Base-768 + kNN(k=8) + 1 layer GCN",
    "occlusion_level": 0,
    "mAP": 72.6729,
    "rank1": 94.27890014648438,
    "rank5": 97.73539733886719,
    "rank10": 98.8676986694336
  },
  {
    "model_name": "ViT+GCN kNN L1",
    "abl_id": "ABL-15",
    "model_group": "ViT-Base",
    "description": "ViT-Base-768 + kNN(k=8) + 1 layer GCN",
    "occlusion_level": 3,
    "mAP": 72.1305,
    "rank1": 94.27890014648438,
    "rank5": 97.73539733886719,
    "rank10": 98.8676986694336
  },
  {
    "model_name": "ViT+GCN kNN L1",
    "abl_id": "ABL-15",
    "model_group": "ViT-Base",
    "description": "ViT-Base-768 + kNN(k=8) + 1 layer GCN",
    "occlusion_level": 6,
    "mAP": 71.888,
    "rank1": 93.68299865722656,
    "rank5": 97.55660247802734,
    "rank10": 98.62930297851562
  },
  {
    "model_name": "ViT+GCN kNN L1",
    "abl_id": "ABL-15",
    "model_group": "ViT-Base",
    "description": "ViT-Base-768 + kNN(k=8) + 1 layer GCN",
    "occlusion_level": 9,
    "mAP": 71.2536,
    "rank1": 93.32540130615234,
    "rank5": 97.31819915771484,
    "rank10": 98.5697021484375
  },
  {
    "model_name": "ViT+GCN kNN L1",
    "abl_id": "ABL-15",
    "model_group": "ViT-Base",
    "description": "ViT-Base-768 + kNN(k=8) + 1 layer GCN",
    "occlusion_level": 12,
    "mAP": 70.5529,
    "rank1": 92.25270080566406,
    "rank5": 97.25859832763672,
    "rank10": 98.74849700927734
  },
  {
    "model_name": "ViT+GCN kNN L1",
    "abl_id": "ABL-15",
    "model_group": "ViT-Base",
    "description": "ViT-Base-768 + kNN(k=8) + 1 layer GCN",
    "occlusion_level": 15,
    "mAP": 69.7102,
    "rank1": 92.43150329589844,
    "rank5": 97.1989974975586,
    "rank10": 98.39089965820312
  },
  {
    "model_name": "ViT+GCN kNN L1",
    "abl_id": "ABL-15",
    "model_group": "ViT-Base",
    "description": "ViT-Base-768 + kNN(k=8) + 1 layer GCN",
    "occlusion_level": 18,
    "mAP": 68.7608,
    "rank1": 91.41840362548828,
    "rank5": 96.54350280761719,
    "rank10": 97.97380065917969
  },
  {
    "model_name": "ViT+GCN kNN L1",
    "abl_id": "ABL-15",
    "model_group": "ViT-Base",
    "description": "ViT-Base-768 + kNN(k=8) + 1 layer GCN",
    "occlusion_level": 21,
    "mAP": 67.9941,
    "rank1": 91.18000030517578,
    "rank5": 96.06680297851562,
    "rank10": 98.09300231933594
  },
  {
    "model_name": "ViT+GCN kNN L1",
    "abl_id": "ABL-15",
    "model_group": "ViT-Base",
    "description": "ViT-Base-768 + kNN(k=8) + 1 layer GCN",
    "occlusion_level": 24,
    "mAP": 67.0333,
    "rank1": 90.58399963378906,
    "rank5": 96.06680297851562,
    "rank10": 97.73539733886719
  },
  {
    "model_name": "ViT+GCN kNN L1",
    "abl_id": "ABL-15",
    "model_group": "ViT-Base",
    "description": "ViT-Base-768 + kNN(k=8) + 1 layer GCN",
    "occlusion_level": 27,
    "mAP": 65.6785,
    "rank1": 89.74970245361328,
    "rank5": 95.58999633789062,
    "rank10": 97.73539733886719
  },
  {
    "model_name": "ViT+GCN kNN L1",
    "abl_id": "ABL-15",
    "model_group": "ViT-Base",
    "description": "ViT-Base-768 + kNN(k=8) + 1 layer GCN",
    "occlusion_level": 30,
    "mAP": 64.9148,
    "rank1": 88.37899780273438,
    "rank5": 95.05359649658203,
    "rank10": 97.13939666748047
  }
]